{"tournamentId": 9203524, "banner": [], "name": "Eighty Nine Trophy V - turniej 14/15", "type": 0, "format": 4, "breakrule": "alternate", "description": "Turniej rankingowy WPT.", "dresscode": "", "defaultRaceTo": 4, "url": "https://cuescore.com/tournament/Eighty+Nine+Trophy+V+-+turniej+14%252F15/9203524", "timezone": "Europe/Warsaw", "displayDate": "August 31, 2021", "starttime": "2021-08-31T19:00:00+02:00", "stoptime": "2021-08-31T23:00:00+02:00", "deadline": "", "entrystart": "", "status": "Finished", "discipline": "9-Ball", "disciplineId": 3, "branch": 1, "handicap": [], "contacts": [{"playerId": 1620195, "name": "Micha\u0142 Nowak", "firstname": "Micha\u0142", "lastname": "Nowak", "url": "https://cuescore.com/player/Micha%C5%82+Nowak/1620195", "image": "https://img.cuescore.com/image/1/4/15d291e83ead350107ae474e8623a6f5.png?t=1504629089", "country": {"name": "Poland", "alpha3": "POL", "image": "https://cuescore.com/img/flags/png-country-4x2-none/res-640x480/pl.png", "continent": "Europe"}, "represents": []}], "owner": {"organizationId": 7011764, "stub": "blackballevents", "name": "Black Ball Events", "url": "https://cuescore.com/blackballevents", "logo": "//img.cuescore.com/image/9/2/9b59b70e156f2f8d0f1a879411c6ffd1.png?t=1576160578", "profileColor": "000000"}, "organizers": [{"organizationId": 7011764, "stub": "blackballevents", "name": "Black Ball Events", "url": "https://cuescore.com/blackballevents", "logo": "//img.cuescore.com/image/9/2/9b59b70e156f2f8d0f1a879411c6ffd1.png?t=1576160578", "profileColor": "000000"}], "venues": [{"venueId": 3367445, "name": "Eighty Nine", "url": "https://cuescore.com/venue/Eighty+Nine/3367445", "owner": {"organizationId": 7011764, "stub": "blackballevents", "name": "Black Ball Events", "url": "https://cuescore.com/blackballevents", "logo": "//img.cuescore.com/image/9/2/9b59b70e156f2f8d0f1a879411c6ffd1.png?t=1576160578", "profileColor": "000000"}}], "sequence": 0, "standings": {"1": [{"position": 1, "player": {"playerId": 1660831, "name": "Sebastian Szymkowski", "firstname": "Sebastian", "lastname": "Szymkowski", "url": "https://cuescore.com/player/Sebastian+Szymkowski/1660831", "image": "https://img.cuescore.com/image/8/4/8e25b60ff30ecb15ccb65e9c5875c024.png?t=1758874499", "country": {"name": "Poland", "alpha3": "POL", "image": "https://cuescore.com/img/flags/png-country-4x2-none/res-640x480/pl.png", "continent": "Europe"}, "represents": []}, "played": 2, "wins": 2, "losses": 0, "ties": 0, "setWins": 0, "setLosses": 0, "setScore": 0, "frameWins": 10, "frameWinAvg": 5, "frameLosses": 5, "frameScore": 5, "frameAvg": 0.667, "innings": 0, "inningAvg": 0, "teamMatchPoints": 0, "teamInnings": 0, "teamInningAvg": 0, "teamBestInningAvg": 0, "teamIndividualPoints": 0, "highBreak": 0, "runouts": 0, "lagWins": 0, "points": 2}, {"position": 2, "player": {"playerId": 8473064, "name": "Damian Tokarski", "firstname": "Damian", "lastname": "Tokarski", "url": "https://cuescore.com/player/Damian+Tokarski/8473064", "image": "https://img.cuescore.com/image/8/4/862c792ba8eb7f97e626fbe6cbcc59f6.png", "country": {"name": "Poland", "alpha3": "POL", "image": "https://cuescore.com/img/flags/png-country-4x2-none/res-640x480/pl.png", "continent": "Europe"}, "represents": []}, "played": 2, "wins": 1, "losses": 1, "ties": 0, "setWins": 0, "setLosses": 0, "setScore": 0, "frameWins": 7, "frameWinAvg": 3.5, "frameLosses": 8, "frameScore": -1, "frameAvg": 0.467, "innings": 0, "inningAvg": 0, "teamMatchPoints": 0, "teamInnings": 0, "teamInningAvg": 0, "teamBestInningAvg": 0, "teamIndividualPoints": 0, "highBreak": 0, "runouts": 0, "lagWins": 0, "points": 1}, {"position": 3, "player": {"playerId": 19794961, "name": "Krzysztof Doroszkiewicz", "firstname": "Krzysztof", "lastname": "Doroszkiewicz", "url": "https://cuescore.com/player/Krzysztof+Doroszkiewicz/19794961", "image": "https://img.cuescore.com/image/8/4/862c792ba8eb7f97e626fbe6cbcc59f6.png", "country": {"name": "Poland", "alpha3": "POL", "image": "https://cuescore.com/img/flags/png-country-4x2-none/res-640x480/pl.png", "continent": "Europe"}, "represents": []}, "played": 2, "wins": 0, "losses": 2, "ties": 0, "setWins": 0, "setLosses": 0, "setScore": 0, "frameWins": 6, "frameWinAvg": 3, "frameLosses": 10, "frameScore": -4, "frameAvg": 0.375, "innings": 0, "inningAvg": 0, "teamMatchPoints": 0, "teamInnings": 0, "teamInningAvg": 0, "teamBestInningAvg": 0, "teamIndividualPoints": 0, "highBreak": 0, "runouts": 0, "lagWins": 0, "points": 0}, {"position": 4, "player": {"playerId": 2098390, "name": "Wolny Los1", "firstname": "Wolny", "lastname": "Los1", "url": "https://cuescore.com/player/Wolny+Los1/2098390", "image": "https://img.cuescore.com/image/8/4/862c792ba8eb7f97e626fbe6cbcc59f6.png", "country": [], "represents": []}, "played": 0, "wins": 0, "losses": 0, "ties": 0, "setWins": 0, "setLosses": 0, "setScore": 0, "frameWins": 0, "frameWinAvg": 0, "frameLosses": 0, "frameScore": 0, "frameAvg": 0, "innings": 0, "inningAvg": 0, "teamMatchPoints": 0, "teamInnings": 0, "teamInningAvg": 0, "teamBestInningAvg": 0, "teamIndividualPoints": 0, "highBreak": 0, "runouts": 0, "lagWins": 0, "points": 0}], "2": [{"position": 1, "player": {"playerId": 2383646, "name": "Piotr Niewczas", "firstname": "Piotr", "lastname": "Niewczas", "url": "https://cuescore.com/player/Piotr+Niewczas/2383646", "image": "https://img.cuescore.com/image/5/4/5859c1d9450d0be5004521cfdb2938c9.png?t=1551456237", "country": {"name": "Poland", "alpha3": "POL", "image": "https://cuescore.com/img/flags/png-country-4x2-none/res-640x480/pl.png", "continent": "Europe"}, "represents": []}, "played": 3, "wins": 3, "losses": 0, "ties": 0, "setWins": 0, "setLosses": 0, "setScore": 0, "frameWins": 12, "frameWinAvg": 4, "frameLosses": 6, "frameScore": 6, "frameAvg": 0.667, "innings": 0, "inningAvg": 0, "teamMatchPoints": 0, "teamInnings": 0, "teamInningAvg": 0, "teamBestInningAvg": 0, "teamIndividualPoints": 0, "highBreak": 0, "runouts": 0, "lagWins": 0, "points": 3}, {"position": 2, "player": {"playerId": 8440979, "name": "Dawid Tonojan", "firstname": "Dawid", "lastname": "Tonojan", "url": "https://cuescore.com/player/Dawid+Tonojan/8440979", "image": "https://img.cuescore.com/image/f/4/f3eaf2f78980cd906e7ab9eb005e0480.png?t=1679557952", "country": {"name": "Poland", "alpha3": "POL", "image": "https://cuescore.com/img/flags/png-country-4x2-none/res-640x480/pl.png", "continent": "Europe"}, "represents": []}, "played": 3, "wins": 2, "losses": 1, "ties": 0, "setWins": 0, "setLosses": 0, "setScore": 0, "frameWins": 10, "frameWinAvg": 3.333, "frameLosses": 7, "frameScore": 3, "frameAvg": 0.588, "innings": 0, "inningAvg": 0, "teamMatchPoints": 0, "teamInnings": 0, "teamInningAvg": 0, "teamBestInningAvg": 0, "teamIndividualPoints": 0, "highBreak": 0, "runouts": 0, "lagWins": 0, "points": 2}, {"position": 3, "player": {"playerId": 8183149, "name": "Filip Mazur", "firstname": "Filip", "lastname": "Mazur", "url": "https://cuescore.com/player/Filip+Mazur/8183149", "image": "https://img.cuescore.com/image/1/4/1192fb9c1781d56b751eb14fdc20663e.png?t=1693751036", "country": {"name": "Poland", "alpha3": "POL", "image": "https://cuescore.com/img/flags/png-country-4x2-none/res-640x480/pl.png", "continent": "Europe"}, "represents": []}, "played": 3, "wins": 1, "losses": 2, "ties": 0, "setWins": 0, "setLosses": 0, "setScore": 0, "frameWins": 5, "frameWinAvg": 1.667, "frameLosses": 10, "frameScore": -5, "frameAvg": 0.333, "innings": 0, "inningAvg": 0, "teamMatchPoints": 0, "teamInnings": 0, "teamInningAvg": 0, "teamBestInningAvg": 0, "teamIndividualPoints": 0, "highBreak": 0, "runouts": 0, "lagWins": 0, "points": 1}, {"position": 4, "player": {"playerId": 5665150, "name": "\u0141ukasz Wojtkowiak", "firstname": "\u0141ukasz", "lastname": "Wojtkowiak", "url": "https://cuescore.com/player/%C5%81ukasz+Wojtkowiak/5665150", "image": "https://img.cuescore.com/image/9/4/98e6516dcca6383eab1da5a079164508.png?t=1565342357", "country": {"name": "Poland", "alpha3": "POL", "image": "https://cuescore.com/img/flags/png-country-4x2-none/res-640x480/pl.png", "continent": "Europe"}, "represents": []}, "played": 3, "wins": 0, "losses": 3, "ties": 0, "setWins": 0, "setLosses": 0, "setScore": 0, "frameWins": 8, "frameWinAvg": 2.667, "frameLosses": 12, "frameScore": -4, "frameAvg": 0.4, "innings": 0, "inningAvg": 0, "teamMatchPoints": 0, "teamInnings": 0, "teamInningAvg": 0, "teamBestInningAvg": 0, "teamIndividualPoints": 0, "highBreak": 0, "runouts": 0, "lagWins": 0, "points": 0}], "3": [{"position": 1, "player": {"playerId": 2180579, "name": "Marta Wawrzyn", "firstname": "Marta", "lastname": "Wawrzyn", "url": "https://cuescore.com/player/Marta+Wawrzyn/2180579", "image": "https://img.cuescore.com/image/e/4/eff8001937f0a627a1c033854110bbe7.png?t=1737981612", "country": {"name": "Poland", "alpha3": "POL", "image": "https://cuescore.com/img/flags/png-country-4x2-none/res-640x480/pl.png", "continent": "Europe"}, "represents": []}, "played": 3, "wins": 3, "losses": 0, "ties": 0, "setWins": 0, "setLosses": 0, "setScore": 0, "frameWins": 12, "frameWinAvg": 4, "frameLosses": 4, "frameScore": 8, "frameAvg": 0.75, "innings": 0, "inningAvg": 0, "teamMatchPoints": 0, "teamInnings": 0, "teamInningAvg": 0, "teamBestInningAvg": 0, "teamIndividualPoints": 0, "highBreak": 0, "runouts": 0, "lagWins": 0, "points": 3}, {"position": 2, "player": {"playerId": 2380196, "name": "Tomasz Stachera", "firstname": "Tomasz", "lastname": "Stachera", "url": "https://cuescore.com/player/Tomasz+Stachera/2380196", "image": "https://img.cuescore.com/image/d/4/d49717b5d8dad07dee1f23f9245e1750.png?t=1580259634", "country": {"name": "Poland", "alpha3": "POL", "image": "https://cuescore.com/img/flags/png-country-4x2-none/res-640x480/pl.png", "continent": "Europe"}, "represents": []}, "played": 3, "wins": 2, "losses": 1, "ties": 0, "setWins": 0, "setLosses": 0, "setScore": 0, "frameWins": 11, "frameWinAvg": 3.667, "frameLosses": 4, "frameScore": 7, "frameAvg": 0.733, "innings": 0, "inningAvg": 0, "teamMatchPoints": 0, "teamInnings": 0, "teamInningAvg": 0, "teamBestInningAvg": 0, "teamIndividualPoints": 0, "highBreak": 0, "runouts": 0, "lagWins": 0, "points": 2}, {"position": 3, "player": {"playerId": 2555617, "name": "Witek Stachera", "firstname": "Witek", "lastname": "Stachera", "url": "https://cuescore.com/player/Witek+Stachera/2555617", "image": "https://img.cuescore.com/image/5/4/5479e32916eecaa8f48b155f7419893e.png?t=1548169639", "country": {"name": "Poland", "alpha3": "POL", "image": "https://cuescore.com/img/flags/png-country-4x2-none/res-640x480/pl.png", "continent": "Europe"}, "represents": []}, "played": 3, "wins": 1, "losses": 2, "ties": 0, "setWins": 0, "setLosses": 0, "setScore": 0, "frameWins": 4, "frameWinAvg": 1.333, "frameLosses": 11, "frameScore": -7, "frameAvg": 0.267, "innings": 0, "inningAvg": 0, "teamMatchPoints": 0, "teamInnings": 0, "teamInningAvg": 0, "teamBestInningAvg": 0, "teamIndividualPoints": 0, "highBreak": 0, "runouts": 0, "lagWins": 0, "points": 1}, {"position": 4, "player": {"playerId": 8846680, "name": "Hubert Biczyk", "firstname": "Hubert", "lastname": "Biczyk", "url": "https://cuescore.com/player/Hubert+Biczyk/8846680", "image": "https://img.cuescore.com/image/8/4/862c792ba8eb7f97e626fbe6cbcc59f6.png", "country": {"name": "Poland", "alpha3": "POL", "image": "https://cuescore.com/img/flags/png-country-4x2-none/res-640x480/pl.png", "continent": "Europe"}, "represents": []}, "played": 3, "wins": 0, "losses": 3, "ties": 0, "setWins": 0, "setLosses": 0, "setScore": 0, "frameWins": 4, "frameWinAvg": 1.333, "frameLosses": 12, "frameScore": -8, "frameAvg": 0.25, "innings": 0, "inningAvg": 0, "teamMatchPoints": 0, "teamInnings": 0, "teamInningAvg": 0, "teamBestInningAvg": 0, "teamIndividualPoints": 0, "highBreak": 0, "runouts": 0, "lagWins": 0, "points": 0}], "4": [{"position": 1, "player": {"playerId": 4890123, "name": "Les\u0142aw \u0141ukaszewicz", "firstname": "Les\u0142aw", "lastname": "\u0141ukaszewicz", "url": "https://cuescore.com/player/Les%C5%82aw+%C5%81ukaszewicz/4890123", "image": "https://img.cuescore.com/image/c/4/c4451d50e12c1b75282716bc9ae69017.png?t=1631561718", "country": {"name": "Poland", "alpha3": "POL", "image": "https://cuescore.com/img/flags/png-country-4x2-none/res-640x480/pl.png", "continent": "Europe"}, "represents": []}, "played": 3, "wins": 3, "losses": 0, "ties": 0, "setWins": 0, "setLosses": 0, "setScore": 0, "frameWins": 12, "frameWinAvg": 4, "frameLosses": 7, "frameScore": 5, "frameAvg": 0.632, "innings": 0, "inningAvg": 0, "teamMatchPoints": 0, "teamInnings": 0, "teamInningAvg": 0, "teamBestInningAvg": 0, "teamIndividualPoints": 0, "highBreak": 0, "runouts": 0, "lagWins": 0, "points": 3}, {"position": 2, "player": {"playerId": 1634586, "name": "Marcin Kubalski", "firstname": "Marcin", "lastname": "Kubalski", "url": "https://cuescore.com/player/Marcin+Kubalski/1634586", "image": "https://img.cuescore.com/image/6/4/634670d25cfb0b8494e08327b2bb74b4.png?t=1736761259", "country": {"name": "Poland", "alpha3": "POL", "image": "https://cuescore.com/img/flags/png-country-4x2-none/res-640x480/pl.png", "continent": "Europe"}, "represents": {"organizationId": 4991658, "stub": "snookerzone", "name": "Snooker.Zone", "url": "https://cuescore.com/snookerzone", "logo": "//img.cuescore.com/image/2/2/2c18635ebc6f2e574949d524d3026197.png?t=1551972415", "profileColor": ""}}, "played": 3, "wins": 1, "losses": 2, "ties": 0, "setWins": 0, "setLosses": 0, "setScore": 0, "frameWins": 9, "frameWinAvg": 3, "frameLosses": 9, "frameScore": 0, "frameAvg": 0.5, "innings": 0, "inningAvg": 0, "teamMatchPoints": 0, "teamInnings": 0, "teamInningAvg": 0, "teamBestInningAvg": 0, "teamIndividualPoints": 0, "highBreak": 0, "runouts": 0, "lagWins": 0, "points": 1}, {"position": 3, "player": {"playerId": 1718455, "name": "Brajan Sawicki", "firstname": "Brajan", "lastname": "Sawicki", "url": "https://cuescore.com/player/Brajan+Sawicki/1718455", "image": "https://img.cuescore.com/image/7/4/7d0eac9908743891ca13c3d70d315319.png?t=1744044465", "country": {"name": "Poland", "alpha3": "POL", "image": "https://cuescore.com/img/flags/png-country-4x2-none/res-640x480/pl.png", "continent": "Europe"}, "represents": []}, "played": 3, "wins": 1, "losses": 2, "ties": 0, "setWins": 0, "setLosses": 0, "setScore": 0, "frameWins": 8, "frameWinAvg": 2.667, "frameLosses": 9, "frameScore": -1, "frameAvg": 0.471, "innings": 0, "inningAvg": 0, "teamMatchPoints": 0, "teamInnings": 0, "teamInningAvg": 0, "teamBestInningAvg": 0, "teamIndividualPoints": 0, "highBreak": 0, "runouts": 0, "lagWins": 0, "points": 1}, {"position": 4, "player": {"playerId": 4895428, "name": "Ewelina Pi\u015blewska", "firstname": "Ewelina", "lastname": "Pi\u015blewska", "url": "https://cuescore.com/player/Ewelina+Pi%C5%9Blewska/4895428", "image": "https://img.cuescore.com/image/7/4/7ca8efed4116a0d94fc6420732710509.png?t=1615748426", "country": {"name": "Poland", "alpha3": "POL", "image": "https://cuescore.com/img/flags/png-country-4x2-none/res-640x480/pl.png", "continent": "Europe"}, "represents": []}, "played": 3, "wins": 1, "losses": 2, "ties": 0, "setWins": 0, "setLosses": 0, "setScore": 0, "frameWins": 6, "frameWinAvg": 2, "frameLosses": 10, "frameScore": -4, "frameAvg": 0.375, "innings": 0, "inningAvg": 0, "teamMatchPoints": 0, "teamInnings": 0, "teamInningAvg": 0, "teamBestInningAvg": 0, "teamIndividualPoints": 0, "highBreak": 0, "runouts": 0, "lagWins": 0, "points": 1}]}, "matches": [{"matchId": 9203957, "matchno": 1, "roundName": "Round 1", "round": 1, "playerA": {"playerId": 1660831, "name": "Sebastian Szymkowski", "firstname": "Sebastian", "lastname": "Szymkowski", "url": "https://cuescore.com/player/Sebastian+Szymkowski/1660831", "image": "https://img.cuescore.com/image/8/4/8e25b60ff30ecb15ccb65e9c5875c024.png?t=1758874499", "country": {"name": "Poland", "alpha3": "POL", "image": "https://cuescore.com/img/flags/png-country-4x2-none/res-640x480/pl.png", "continent": "Europe"}, "represents": []}, "playerB": {"playerId": 8473064, "name": "Damian Tokarski", "firstname": "Damian", "lastname": "Tokarski", "url": "https://cuescore.com/player/Damian+Tokarski/8473064", "image": "https://img.cuescore.com/image/8/4/862c792ba8eb7f97e626fbe6cbcc59f6.png", "country": {"name": "Poland", "alpha3": "POL", "image": "https://cuescore.com/img/flags/png-country-4x2-none/res-640x480/pl.png", "continent": "Europe"}, "represents": []}, "scoreA": 5, "scoreB": 2, "raceTo": 4, "discipline": "9-Ball", "disciplineId": 3, "branch": 1, "penalty": 0, "groupNo": 1, "inningsPlayerA": 0, "inningsPlayerB": 0, "highBreaksA": "", "highBreaksB": "", "runoutsA": 0, "runoutsB": 0, "lagWinner": "", "table": [], "tournamentId": 9203524, "challengeId": 0, "starttime": "2021-08-31T20:28:00", "stoptime": "2021-08-31T21:02:03", "matchstatus": "finished", "matchstatusCode": 2, "bestOfSets": 0, "useInnings": false, "frames": [], "properties": [], "sets": [], "curVersion": 85, "notes": [], "matchType": 0, "videoLink": "", "comment": "", "winnerNext": "", "loserNext": ""}, {"matchId": 9203958, "matchno": 2, "roundName": "Round 1", "round": 1, "playerA": {"playerId": 2098390, "name": "Wolny Los1", "firstname": "Wolny", "lastname": "Los1", "url": "https://cuescore.com/player/Wolny+Los1/2098390", "image": "https://img.cuescore.com/image/8/4/862c792ba8eb7f97e626fbe6cbcc59f6.png", "country": [], "represents": []}, "playerB": {"playerId": 19794961, "name": "Krzysztof Doroszkiewicz", "firstname": "Krzysztof", "lastname": "Doroszkiewicz", "url": "https://cuescore.com/player/Krzysztof+Doroszkiewicz/19794961", "image": "https://img.cuescore.com/image/8/4/862c792ba8eb7f97e626fbe6cbcc59f6.png", "country": {"name": "Poland", "alpha3": "POL", "image": "https://cuescore.com/img/flags/png-country-4x2-none/res-640x480/pl.png", "continent": "Europe"}, "represents": []}, "scoreA": 0, "scoreB": 0, "raceTo": 4, "discipline": "9-Ball", "disciplineId": 3, "branch": 1, "penalty": 1, "groupNo": 1, "inningsPlayerA": 0, "inningsPlayerB": 0, "highBreaksA": "", "highBreaksB": "", "runoutsA": 0, "runoutsB": 0, "lagWinner": "", "table": [], "tournamentId": 9203524, "challengeId": 0, "starttime": "", "stoptime": "", "matchstatus": "finished", "matchstatusCode": 2, "bestOfSets": 0, "useInnings": false, "frames": [], "properties": {"penalty": {"invalid": false, "description": ""}}, "sets": [], "curVersion": 85, "notes": [], "matchType": 0, "videoLink": "", "comment": "", "winnerNext": "", "loserNext": ""}, {"matchId": 9203959, "matchno": 3, "roundName": "Round 1", "round": 1, "playerA": {"playerId": 8440979, "name": "Dawid Tonojan", "firstname": "Dawid", "lastname": "Tonojan", "url": "https://cuescore.com/player/Dawid+Tonojan/8440979", "image": "https://img.cuescore.com/image/f/4/f3eaf2f78980cd906e7ab9eb005e0480.png?t=1679557952", "country": {"name": "Poland", "alpha3": "POL", "image": "https://cuescore.com/img/flags/png-country-4x2-none/res-640x480/pl.png", "continent": "Europe"}, "represents": []}, "playerB": {"playerId": 2383646, "name": "Piotr Niewczas", "firstname": "Piotr", "lastname": "Niewczas", "url": "https://cuescore.com/player/Piotr+Niewczas/2383646", "image": "https://img.cuescore.com/image/5/4/5859c1d9450d0be5004521cfdb2938c9.png?t=1551456237", "country": {"name": "Poland", "alpha3": "POL", "image": "https://cuescore.com/img/flags/png-country-4x2-none/res-640x480/pl.png", "continent": "Europe"}, "represents": []}, "scoreA": 2, "scoreB": 4, "raceTo": 4, "discipline": "9-Ball", "disciplineId": 3, "branch": 1, "penalty": 0, "groupNo": 2, "inningsPlayerA": 0, "inningsPlayerB": 0, "highBreaksA": "", "highBreaksB": "", "runoutsA": 0, "runoutsB": 0, "lagWinner": "", "table": [], "tournamentId": 9203524, "challengeId": 0, "starttime": "2021-08-31T20:35:00", "stoptime": "2021-08-31T21:05:05", "matchstatus": "finished", "matchstatusCode": 2, "bestOfSets": 0, "useInnings": false, "frames": [], "properties": [], "sets": [], "curVersion": 85, "notes": [], "matchType": 0, "videoLink": "", "comment": "", "winnerNext": "", "loserNext": ""}, {"matchId": 9203960, "matchno": 4, "roundName": "Round 1", "round": 1, "playerA": {"playerId": 8183149, "name": "Filip Mazur", "firstname": "Filip", "lastname": "Mazur", "url": "https://cuescore.com/player/Filip+Mazur/8183149", "image": "https://img.cuescore.com/image/1/4/1192fb9c1781d56b751eb14fdc20663e.png?t=1693751036", "country": {"name": "Poland", "alpha3": "POL", "image": "https://cuescore.com/img/flags/png-country-4x2-none/res-640x480/pl.png", "continent": "Europe"}, "represents": []}, "playerB": {"playerId": 5665150, "name": "\u0141ukasz Wojtkowiak", "firstname": "\u0141ukasz", "lastname": "Wojtkowiak", "url": "https://cuescore.com/player/%C5%81ukasz+Wojtkowiak/5665150", "image": "https://img.cuescore.com/image/9/4/98e6516dcca6383eab1da5a079164508.png?t=1565342357", "country": {"name": "Poland", "alpha3": "POL", "image": "https://cuescore.com/img/flags/png-country-4x2-none/res-640x480/pl.png", "continent": "Europe"}, "represents": []}, "scoreA": 4, "scoreB": 2, "raceTo": 4, "discipline": "9-Ball", "disciplineId": 3, "branch": 1, "penalty": 0, "groupNo": 2, "inningsPlayerA": 0, "inningsPlayerB": 0, "highBreaksA": "", "highBreaksB": "", "runoutsA": 0, "runoutsB": 0, "lagWinner": "", "table": [], "tournamentId": 9203524, "challengeId": 0, "starttime": "2021-08-31T20:35:00", "stoptime": "2021-08-31T21:08:33", "matchstatus": "finished", "matchstatusCode": 2, "bestOfSets": 0, "useInnings": false, "frames": [], "properties": [], "sets": [], "curVersion": 85, "notes": [], "matchType": 0, "videoLink": "", "comment": "", "winnerNext": "", "loserNext": ""}, {"matchId": 9203961, "matchno": 5, "roundName": "Round 1", "round": 1, "playerA": {"playerId": 2380196, "name": "Tomasz Stachera", "firstname": "Tomasz", "lastname": "Stachera", "url": "https://cuescore.com/player/Tomasz+Stachera/2380196", "image": "https://img.cuescore.com/image/d/4/d49717b5d8dad07dee1f23f9245e1750.png?t=1580259634", "country": {"name": "Poland", "alpha3": "POL", "image": "https://cuescore.com/img/flags/png-country-4x2-none/res-640x480/pl.png", "continent": "Europe"}, "represents": []}, "playerB": {"playerId": 2555617, "name": "Witek Stachera", "firstname": "Witek", "lastname": "Stachera", "url": "https://cuescore.com/player/Witek+Stachera/2555617", "image": "https://img.cuescore.com/image/5/4/5479e32916eecaa8f48b155f7419893e.png?t=1548169639", "country": {"name": "Poland", "alpha3": "POL", "image": "https://cuescore.com/img/flags/png-country-4x2-none/res-640x480/pl.png", "continent": "Europe"}, "represents": []}, "scoreA": 4, "scoreB": 0, "raceTo": 4, "discipline": "9-Ball", "disciplineId": 3, "branch": 1, "penalty": 0, "groupNo": 3, "inningsPlayerA": 0, "inningsPlayerB": 0, "highBreaksA": "", "highBreaksB": "", "runoutsA": 0, "runoutsB": 0, "lagWinner": "", "table": [], "tournamentId": 9203524, "challengeId": 0, "starttime": "2021-08-31T20:10:00", "stoptime": "2021-08-31T20:34:05", "matchstatus": "finished", "matchstatusCode": 2, "bestOfSets": 0, "useInnings": false, "frames": [], "properties": [], "sets": [], "curVersion": 85, "notes": [], "matchType": 0, "videoLink": "", "comment": "", "winnerNext": "", "loserNext": ""}, {"matchId": 9203962, "matchno": 6, "roundName": "Round 1", "round": 1, "playerA": {"playerId": 8846680, "name": "Hubert Biczyk", "firstname": "Hubert", "lastname": "Biczyk", "url": "https://cuescore.com/player/Hubert+Biczyk/8846680", "image": "https://img.cuescore.com/image/8/4/862c792ba8eb7f97e626fbe6cbcc59f6.png", "country": {"name": "Poland", "alpha3": "POL", "image": "https://cuescore.com/img/flags/png-country-4x2-none/res-640x480/pl.png", "continent": "Europe"}, "represents": []}, "playerB": {"playerId": 2180579, "name": "Marta Wawrzyn", "firstname": "Marta", "lastname": "Wawrzyn", "url": "https://cuescore.com/player/Marta+Wawrzyn/2180579", "image": "https://img.cuescore.com/image/e/4/eff8001937f0a627a1c033854110bbe7.png?t=1737981612", "country": {"name": "Poland", "alpha3": "POL", "image": "https://cuescore.com/img/flags/png-country-4x2-none/res-640x480/pl.png", "continent": "Europe"}, "represents": []}, "scoreA": 1, "scoreB": 4, "raceTo": 4, "discipline": "9-Ball", "disciplineId": 3, "branch": 1, "penalty": 0, "groupNo": 3, "inningsPlayerA": 0, "inningsPlayerB": 0, "highBreaksA": "", "highBreaksB": "", "runoutsA": 0, "runoutsB": 0, "lagWinner": "", "table": [], "tournamentId": 9203524, "challengeId": 0, "starttime": "2021-08-31T20:28:00", "stoptime": "2021-08-31T21:02:28", "matchstatus": "finished", "matchstatusCode": 2, "bestOfSets": 0, "useInnings": false, "frames": [], "properties": [], "sets": [], "curVersion": 85, "notes": [], "matchType": 0, "videoLink": "", "comment": "", "winnerNext": "", "loserNext": ""}, {"matchId": 9203963, "matchno": 7, "roundName": "Round 1", "round": 1, "playerA": {"playerId": 1634586, "name": "Marcin Kubalski", "firstname": "Marcin", "lastname": "Kubalski", "url": "https://cuescore.com/player/Marcin+Kubalski/1634586", "image": "https://img.cuescore.com/image/6/4/634670d25cfb0b8494e08327b2bb74b4.png?t=1736761259", "country": {"name": "Poland", "alpha3": "POL", "image": "https://cuescore.com/img/flags/png-country-4x2-none/res-640x480/pl.png", "continent": "Europe"}, "represents": {"organizationId": 4991658, "stub": "snookerzone", "name": "Snooker.Zone", "url": "https://cuescore.com/snookerzone", "logo": "//img.cuescore.com/image/2/2/2c18635ebc6f2e574949d524d3026197.png?t=1551972415", "profileColor": ""}}, "playerB": {"playerId": 1718455, "name": "Brajan Sawicki", "firstname": "Brajan", "lastname": "Sawicki", "url": "https://cuescore.com/player/Brajan+Sawicki/1718455", "image": "https://img.cuescore.com/image/7/4/7d0eac9908743891ca13c3d70d315319.png?t=1744044465", "country": {"name": "Poland", "alpha3": "POL", "image": "https://cuescore.com/img/flags/png-country-4x2-none/res-640x480/pl.png", "continent": "Europe"}, "represents": []}, "scoreA": 4, "scoreB": 1, "raceTo": 4, "discipline": "9-Ball", "disciplineId": 3, "branch": 1, "penalty": 0, "groupNo": 4, "inningsPlayerA": 0, "inningsPlayerB": 0, "highBreaksA": "", "highBreaksB": "", "runoutsA": 0, "runoutsB": 0, "lagWinner": "", "table": [], "tournamentId": 9203524, "challengeId": 0, "starttime": "2021-08-31T19:53:00", "stoptime": "2021-08-31T20:33:20", "matchstatus": "finished", "matchstatusCode": 2, "bestOfSets": 0, "useInnings": false, "frames": [], "properties": [], "sets": [], "curVersion": 85, "notes": [], "matchType": 0, "videoLink": "", "comment": "", "winnerNext": "", "loserNext": ""}, {"matchId": 9203964, "matchno": 8, "roundName": "Round 1", "round": 1, "playerA": {"playerId": 4890123, "name": "Les\u0142aw \u0141ukaszewicz", "firstname": "Les\u0142aw", "lastname": "\u0141ukaszewicz", "url": "https://cuescore.com/player/Les%C5%82aw+%C5%81ukaszewicz/4890123", "image": "https://img.cuescore.com/image/c/4/c4451d50e12c1b75282716bc9ae69017.png?t=1631561718", "country": {"name": "Poland", "alpha3": "POL", "image": "https://cuescore.com/img/flags/png-country-4x2-none/res-640x480/pl.png", "continent": "Europe"}, "represents": []}, "playerB": {"playerId": 4895428, "name": "Ewelina Pi\u015blewska", "firstname": "Ewelina", "lastname": "Pi\u015blewska", "url": "https://cuescore.com/player/Ewelina+Pi%C5%9Blewska/4895428", "image": "https://img.cuescore.com/image/7/4/7ca8efed4116a0d94fc6420732710509.png?t=1615748426", "country": {"name": "Poland", "alpha3": "POL", "image": "https://cuescore.com/img/flags/png-country-4x2-none/res-640x480/pl.png", "continent": "Europe"}, "represents": []}, "scoreA": 4, "scoreB": 1, "raceTo": 4, "discipline": "9-Ball", "disciplineId": 3, "branch": 1, "penalty": 0, "groupNo": 4, "inningsPlayerA": 0, "inningsPlayerB": 0, "highBreaksA": "", "highBreaksB": "", "runoutsA": 0, "runoutsB": 0, "lagWinner": "", "table": [], "tournamentId": 9203524, "challengeId": 0, "starttime": "2021-08-31T20:03:00", "stoptime": "2021-08-31T20:27:51", "matchstatus": "finished", "matchstatusCode": 2, "bestOfSets": 0, "useInnings": false, "frames": [], "properties": [], "sets": [], "curVersion": 85, "notes": [], "matchType": 0, "videoLink": "", "comment": "", "winnerNext": "", "loserNext": ""}, {"matchId": 9203965, "matchno": 9, "roundName": "Round 2", "round": 2, "playerA": {"playerId": 1660831, "name": "Sebastian Szymkowski", "firstname": "Sebastian", "lastname": "Szymkowski", "url": "https://cuescore.com/player/Sebastian+Szymkowski/1660831", "image": "https://img.cuescore.com/image/8/4/8e25b60ff30ecb15ccb65e9c5875c024.png?t=1758874499", "country": {"name": "Poland", "alpha3": "POL", "image": "https://cuescore.com/img/flags/png-country-4x2-none/res-640x480/pl.png", "continent": "Europe"}, "represents": []}, "playerB": {"playerId": 19794961, "name": "Krzysztof Doroszkiewicz", "firstname": "Krzysztof", "lastname": "Doroszkiewicz", "url": "https://cuescore.com/player/Krzysztof+Doroszkiewicz/19794961", "image": "https://img.cuescore.com/image/8/4/862c792ba8eb7f97e626fbe6cbcc59f6.png", "country": {"name": "Poland", "alpha3": "POL", "image": "https://cuescore.com/img/flags/png-country-4x2-none/res-640x480/pl.png", "continent": "Europe"}, "represents": []}, "scoreA": 5, "scoreB": 3, "raceTo": 4, "discipline": "9-Ball", "disciplineId": 3, "branch": 1, "penalty": 0, "groupNo": 1, "inningsPlayerA": 0, "inningsPlayerB": 0, "highBreaksA": "", "highBreaksB": "", "runoutsA": 0, "runoutsB": 0, "lagWinner": "", "table": [], "tournamentId": 9203524, "challengeId": 0, "starttime": "2021-08-31T21:02:00", "stoptime": "2021-08-31T21:30:10", "matchstatus": "finished", "matchstatusCode": 2, "bestOfSets": 0, "useInnings": false, "frames": [], "properties": [], "sets": [], "curVersion": 85, "notes": [], "matchType": 0, "videoLink": "", "comment": "", "winnerNext": "", "loserNext": ""}, {"matchId": 9203966, "matchno": 10, "roundName": "Round 2", "round": 2, "playerA": {"playerId": 8473064, "name": "Damian Tokarski", "firstname": "Damian", "lastname": "Tokarski", "url": "https://cuescore.com/player/Damian+Tokarski/8473064", "image": "https://img.cuescore.com/image/8/4/862c792ba8eb7f97e626fbe6cbcc59f6.png", "country": {"name": "Poland", "alpha3": "POL", "image": "https://cuescore.com/img/flags/png-country-4x2-none/res-640x480/pl.png", "continent": "Europe"}, "represents": []}, "playerB": {"playerId": 2098390, "name": "Wolny Los1", "firstname": "Wolny", "lastname": "Los1", "url": "https://cuescore.com/player/Wolny+Los1/2098390", "image": "https://img.cuescore.com/image/8/4/862c792ba8eb7f97e626fbe6cbcc59f6.png", "country": [], "represents": []}, "scoreA": 0, "scoreB": 0, "raceTo": 4, "discipline": "9-Ball", "disciplineId": 3, "branch": 1, "penalty": 2, "groupNo": 1, "inningsPlayerA": 0, "inningsPlayerB": 0, "highBreaksA": "", "highBreaksB": "", "runoutsA": 0, "runoutsB": 0, "lagWinner": "", "table": [], "tournamentId": 9203524, "challengeId": 0, "starttime": "", "stoptime": "", "matchstatus": "finished", "matchstatusCode": 2, "bestOfSets": 0, "useInnings": false, "frames": [], "properties": {"penalty": {"invalid": false, "description": ""}}, "sets": [], "curVersion": 85, "notes": [], "matchType": 0, "videoLink": "", "comment": "", "winnerNext": "", "loserNext": ""}, {"matchId": 9203967, "matchno": 11, "roundName": "Round 2", "round": 2, "playerA": {"playerId": 8440979, "name": "Dawid Tonojan", "firstname": "Dawid", "lastname": "Tonojan", "url": "https://cuescore.com/player/Dawid+Tonojan/8440979", "image": "https://img.cuescore.com/image/f/4/f3eaf2f78980cd906e7ab9eb005e0480.png?t=1679557952", "country": {"name": "Poland", "alpha3": "POL", "image": "https://cuescore.com/img/flags/png-country-4x2-none/res-640x480/pl.png", "continent": "Europe"}, "represents": []}, "playerB": {"playerId": 5665150, "name": "\u0141ukasz Wojtkowiak", "firstname": "\u0141ukasz", "lastname": "Wojtkowiak", "url": "https://cuescore.com/player/%C5%81ukasz+Wojtkowiak/5665150", "image": "https://img.cuescore.com/image/9/4/98e6516dcca6383eab1da5a079164508.png?t=1565342357", "country": {"name": "Poland", "alpha3": "POL", "image": "https://cuescore.com/img/flags/png-country-4x2-none/res-640x480/pl.png", "continent": "Europe"}, "represents": []}, "scoreA": 4, "scoreB": 3, "raceTo": 4, "discipline": "9-Ball", "disciplineId": 3, "branch": 1, "penalty": 0, "groupNo": 2, "inningsPlayerA": 0, "inningsPlayerB": 0, "highBreaksA": "", "highBreaksB": "", "runoutsA": 0, "runoutsB": 0, "lagWinner": "", "table": [], "tournamentId": 9203524, "challengeId": 0, "starttime": "2021-08-31T19:27:00", "stoptime": "2021-08-31T20:03:10", "matchstatus": "finished", "matchstatusCode": 2, "bestOfSets": 0, "useInnings": false, "frames": [], "properties": [], "sets": [], "curVersion": 85, "notes": [], "matchType": 0, "videoLink": "", "comment": "", "winnerNext": "", "loserNext": ""}, {"matchId": 9203968, "matchno": 12, "roundName": "Round 2", "round": 2, "playerA": {"playerId": 2383646, "name": "Piotr Niewczas", "firstname": "Piotr", "lastname": "Niewczas", "url": "https://cuescore.com/player/Piotr+Niewczas/2383646", "image": "https://img.cuescore.com/image/5/4/5859c1d9450d0be5004521cfdb2938c9.png?t=1551456237", "country": {"name": "Poland", "alpha3": "POL", "image": "https://cuescore.com/img/flags/png-country-4x2-none/res-640x480/pl.png", "continent": "Europe"}, "represents": []}, "playerB": {"playerId": 8183149, "name": "Filip Mazur", "firstname": "Filip", "lastname": "Mazur", "url": "https://cuescore.com/player/Filip+Mazur/8183149", "image": "https://img.cuescore.com/image/1/4/1192fb9c1781d56b751eb14fdc20663e.png?t=1693751036", "country": {"name": "Poland", "alpha3": "POL", "image": "https://cuescore.com/img/flags/png-country-4x2-none/res-640x480/pl.png", "continent": "Europe"}, "represents": []}, "scoreA": 4, "scoreB": 1, "raceTo": 4, "discipline": "9-Ball", "disciplineId": 3, "branch": 1, "penalty": 0, "groupNo": 2, "inningsPlayerA": 0, "inningsPlayerB": 0, "highBreaksA": "", "highBreaksB": "", "runoutsA": 0, "runoutsB": 0, "lagWinner": "", "table": [], "tournamentId": 9203524, "challengeId": 0, "starttime": "2021-08-31T19:38:00", "stoptime": "2021-08-31T20:12:37", "matchstatus": "finished", "matchstatusCode": 2, "bestOfSets": 0, "useInnings": false, "frames": [], "properties": [], "sets": [], "curVersion": 85, "notes": [], "matchType": 0, "videoLink": "", "comment": "", "winnerNext": "", "loserNext": ""}, {"matchId": 9203969, "matchno": 13, "roundName": "Round 2", "round": 2, "playerA": {"playerId": 2380196, "name": "Tomasz Stachera", "firstname": "Tomasz", "lastname": "Stachera", "url": "https://cuescore.com/player/Tomasz+Stachera/2380196", "image": "https://img.cuescore.com/image/d/4/d49717b5d8dad07dee1f23f9245e1750.png?t=1580259634", "country": {"name": "Poland", "alpha3": "POL", "image": "https://cuescore.com/img/flags/png-country-4x2-none/res-640x480/pl.png", "continent": "Europe"}, "represents": []}, "playerB": {"playerId": 2180579, "name": "Marta Wawrzyn", "firstname": "Marta", "lastname": "Wawrzyn", "url": "https://cuescore.com/player/Marta+Wawrzyn/2180579", "image": "https://img.cuescore.com/image/e/4/eff8001937f0a627a1c033854110bbe7.png?t=1737981612", "country": {"name": "Poland", "alpha3": "POL", "image": "https://cuescore.com/img/flags/png-country-4x2-none/res-640x480/pl.png", "continent": "Europe"}, "represents": []}, "scoreA": 3, "scoreB": 4, "raceTo": 4, "discipline": "9-Ball", "disciplineId": 3, "branch": 1, "penalty": 0, "groupNo": 3, "inningsPlayerA": 0, "inningsPlayerB": 0, "highBreaksA": "", "highBreaksB": "", "runoutsA": 0, "runoutsB": 0, "lagWinner": "", "table": [], "tournamentId": 9203524, "challengeId": 0, "starttime": "2021-08-31T21:02:00", "stoptime": "2021-08-31T21:38:06", "matchstatus": "finished", "matchstatusCode": 2, "bestOfSets": 0, "useInnings": false, "frames": [], "properties": [], "sets": [], "curVersion": 85, "notes": [], "matchType": 0, "videoLink": "", "comment": "", "winnerNext": "", "loserNext": ""}, {"matchId": 9203970, "matchno": 14, "roundName": "Round 2", "round": 2, "playerA": {"playerId": 2555617, "name": "Witek Stachera", "firstname": "Witek", "lastname": "Stachera", "url": "https://cuescore.com/player/Witek+Stachera/2555617", "image": "https://img.cuescore.com/image/5/4/5479e32916eecaa8f48b155f7419893e.png?t=1548169639", "country": {"name": "Poland", "alpha3": "POL", "image": "https://cuescore.com/img/flags/png-country-4x2-none/res-640x480/pl.png", "continent": "Europe"}, "represents": []}, "playerB": {"playerId": 8846680, "name": "Hubert Biczyk", "firstname": "Hubert", "lastname": "Biczyk", "url": "https://cuescore.com/player/Hubert+Biczyk/8846680", "image": "https://img.cuescore.com/image/8/4/862c792ba8eb7f97e626fbe6cbcc59f6.png", "country": {"name": "Poland", "alpha3": "POL", "image": "https://cuescore.com/img/flags/png-country-4x2-none/res-640x480/pl.png", "continent": "Europe"}, "represents": []}, "scoreA": 4, "scoreB": 3, "raceTo": 4, "discipline": "9-Ball", "disciplineId": 3, "branch": 1, "penalty": 0, "groupNo": 3, "inningsPlayerA": 0, "inningsPlayerB": 0, "highBreaksA": "", "highBreaksB": "", "runoutsA": 0, "runoutsB": 0, "lagWinner": "", "table": [], "tournamentId": 9203524, "challengeId": 0, "starttime": "2021-08-31T21:30:00", "stoptime": "2021-08-31T21:52:56", "matchstatus": "finished", "matchstatusCode": 2, "bestOfSets": 0, "useInnings": false, "frames": [], "properties": {"penalty": []}, "sets": [], "curVersion": 85, "notes": [], "matchType": 0, "videoLink": "", "comment": "", "winnerNext": "", "loserNext": ""}, {"matchId": 9203971, "matchno": 15, "roundName": "Round 2", "round": 2, "playerA": {"playerId": 1634586, "name": "Marcin Kubalski", "firstname": "Marcin", "lastname": "Kubalski", "url": "https://cuescore.com/player/Marcin+Kubalski/1634586", "image": "https://img.cuescore.com/image/6/4/634670d25cfb0b8494e08327b2bb74b4.png?t=1736761259", "country": {"name": "Poland", "alpha3": "POL", "image": "https://cuescore.com/img/flags/png-country-4x2-none/res-640x480/pl.png", "continent": "Europe"}, "represents": {"organizationId": 4991658, "stub": "snookerzone", "name": "Snooker.Zone", "url": "https://cuescore.com/snookerzone", "logo": "//img.cuescore.com/image/2/2/2c18635ebc6f2e574949d524d3026197.png?t=1551972415", "profileColor": ""}}, "playerB": {"playerId": 4895428, "name": "Ewelina Pi\u015blewska", "firstname": "Ewelina", "lastname": "Pi\u015blewska", "url": "https://cuescore.com/player/Ewelina+Pi%C5%9Blewska/4895428", "image": "https://img.cuescore.com/image/7/4/7ca8efed4116a0d94fc6420732710509.png?t=1615748426", "country": {"name": "Poland", "alpha3": "POL", "image": "https://cuescore.com/img/flags/png-country-4x2-none/res-640x480/pl.png", "continent": "Europe"}, "represents": []}, "scoreA": 2, "scoreB": 4, "raceTo": 4, "discipline": "9-Ball", "disciplineId": 3, "branch": 1, "penalty": 0, "groupNo": 4, "inningsPlayerA": 0, "inningsPlayerB": 0, "highBreaksA": "", "highBreaksB": "", "runoutsA": 0, "runoutsB": 0, "lagWinner": "", "table": [], "tournamentId": 9203524, "challengeId": 0, "starttime": "2021-08-31T21:03:00", "stoptime": "2021-08-31T21:38:52", "matchstatus": "finished", "matchstatusCode": 2, "bestOfSets": 0, "useInnings": false, "frames": [], "properties": [], "sets": [], "curVersion": 85, "notes": [], "matchType": 0, "videoLink": "", "comment": "", "winnerNext": "", "loserNext": ""}, {"matchId": 9203972, "matchno": 16, "roundName": "Round 2", "round": 2, "playerA": {"playerId": 1718455, "name": "Brajan Sawicki", "firstname": "Brajan", "lastname": "Sawicki", "url": "https://cuescore.com/player/Brajan+Sawicki/1718455", "image": "https://img.cuescore.com/image/7/4/7d0eac9908743891ca13c3d70d315319.png?t=1744044465", "country": {"name": "Poland", "alpha3": "POL", "image": "https://cuescore.com/img/flags/png-country-4x2-none/res-640x480/pl.png", "continent": "Europe"}, "represents": []}, "playerB": {"playerId": 4890123, "name": "Les\u0142aw \u0141ukaszewicz", "firstname": "Les\u0142aw", "lastname": "\u0141ukaszewicz", "url": "https://cuescore.com/player/Les%C5%82aw+%C5%81ukaszewicz/4890123", "image": "https://img.cuescore.com/image/c/4/c4451d50e12c1b75282716bc9ae69017.png?t=1631561718", "country": {"name": "Poland", "alpha3": "POL", "image": "https://cuescore.com/img/flags/png-country-4x2-none/res-640x480/pl.png", "continent": "Europe"}, "represents": []}, "scoreA": 3, "scoreB": 4, "raceTo": 4, "discipline": "9-Ball", "disciplineId": 3, "branch": 1, "penalty": 0, "groupNo": 4, "inningsPlayerA": 0, "inningsPlayerB": 0, "highBreaksA": "", "highBreaksB": "", "runoutsA": 0, "runoutsB": 0, "lagWinner": "", "table": [], "tournamentId": 9203524, "challengeId": 0, "starttime": "2021-08-31T21:03:00", "stoptime": "2021-08-31T21:48:03", "matchstatus": "finished", "matchstatusCode": 2, "bestOfSets": 0, "useInnings": false, "frames": [], "properties": [], "sets": [], "curVersion": 85, "notes": [], "matchType": 0, "videoLink": "", "comment": "", "winnerNext": "", "loserNext": ""}, {"matchId": 9203973, "matchno": 17, "roundName": "Round 3", "round": 3, "playerA": {"playerId": 1660831, "name": "Sebastian Szymkowski", "firstname": "Sebastian", "lastname": "Szymkowski", "url": "https://cuescore.com/player/Sebastian+Szymkowski/1660831", "image": "https://img.cuescore.com/image/8/4/8e25b60ff30ecb15ccb65e9c5875c024.png?t=1758874499", "country": {"name": "Poland", "alpha3": "POL", "image": "https://cuescore.com/img/flags/png-country-4x2-none/res-640x480/pl.png", "continent": "Europe"}, "represents": []}, "playerB": {"playerId": 2098390, "name": "Wolny Los1", "firstname": "Wolny", "lastname": "Los1", "url": "https://cuescore.com/player/Wolny+Los1/2098390", "image": "https://img.cuescore.com/image/8/4/862c792ba8eb7f97e626fbe6cbcc59f6.png", "country": [], "represents": []}, "scoreA": 0, "scoreB": 0, "raceTo": 4, "discipline": "9-Ball", "disciplineId": 3, "branch": 1, "penalty": 2, "groupNo": 1, "inningsPlayerA": 0, "inningsPlayerB": 0, "highBreaksA": "", "highBreaksB": "", "runoutsA": 0, "runoutsB": 0, "lagWinner": "", "table": [], "tournamentId": 9203524, "challengeId": 0, "starttime": "", "stoptime": "", "matchstatus": "finished", "matchstatusCode": 2, "bestOfSets": 0, "useInnings": false, "frames": [], "properties": {"penalty": {"invalid": false, "description": ""}}, "sets": [], "curVersion": 85, "notes": [], "matchType": 0, "videoLink": "", "comment": "", "winnerNext": "", "loserNext": ""}, {"matchId": 9203974, "matchno": 18, "roundName": "Round 3", "round": 3, "playerA": {"playerId": 19794961, "name": "Krzysztof Doroszkiewicz", "firstname": "Krzysztof", "lastname": "Doroszkiewicz", "url": "https://cuescore.com/player/Krzysztof+Doroszkiewicz/19794961", "image": "https://img.cuescore.com/image/8/4/862c792ba8eb7f97e626fbe6cbcc59f6.png", "country": {"name": "Poland", "alpha3": "POL", "image": "https://cuescore.com/img/flags/png-country-4x2-none/res-640x480/pl.png", "continent": "Europe"}, "represents": []}, "playerB": {"playerId": 8473064, "name": "Damian Tokarski", "firstname": "Damian", "lastname": "Tokarski", "url": "https://cuescore.com/player/Damian+Tokarski/8473064", "image": "https://img.cuescore.com/image/8/4/862c792ba8eb7f97e626fbe6cbcc59f6.png", "country": {"name": "Poland", "alpha3": "POL", "image": "https://cuescore.com/img/flags/png-country-4x2-none/res-640x480/pl.png", "continent": "Europe"}, "represents": []}, "scoreA": 3, "scoreB": 5, "raceTo": 4, "discipline": "9-Ball", "disciplineId": 3, "branch": 1, "penalty": 0, "groupNo": 1, "inningsPlayerA": 0, "inningsPlayerB": 0, "highBreaksA": "", "highBreaksB": "", "runoutsA": 0, "runoutsB": 0, "lagWinner": "", "table": [], "tournamentId": 9203524, "challengeId": 0, "starttime": "2021-08-31T19:19:00", "stoptime": "2021-08-31T20:28:52", "matchstatus": "finished", "matchstatusCode": 2, "bestOfSets": 0, "useInnings": false, "frames": [], "properties": {"penalty": []}, "sets": [], "curVersion": 85, "notes": [], "matchType": 0, "videoLink": "", "comment": "", "winnerNext": "", "loserNext": ""}, {"matchId": 9203975, "matchno": 19, "roundName": "Round 3", "round": 3, "playerA": {"playerId": 8440979, "name": "Dawid Tonojan", "firstname": "Dawid", "lastname": "Tonojan", "url": "https://cuescore.com/player/Dawid+Tonojan/8440979", "image": "https://img.cuescore.com/image/f/4/f3eaf2f78980cd906e7ab9eb005e0480.png?t=1679557952", "country": {"name": "Poland", "alpha3": "POL", "image": "https://cuescore.com/img/flags/png-country-4x2-none/res-640x480/pl.png", "continent": "Europe"}, "represents": []}, "playerB": {"playerId": 8183149, "name": "Filip Mazur", "firstname": "Filip", "lastname": "Mazur", "url": "https://cuescore.com/player/Filip+Mazur/8183149", "image": "https://img.cuescore.com/image/1/4/1192fb9c1781d56b751eb14fdc20663e.png?t=1693751036", "country": {"name": "Poland", "alpha3": "POL", "image": "https://cuescore.com/img/flags/png-country-4x2-none/res-640x480/pl.png", "continent": "Europe"}, "represents": []}, "scoreA": 4, "scoreB": 0, "raceTo": 4, "discipline": "9-Ball", "disciplineId": 3, "branch": 1, "penalty": 0, "groupNo": 2, "inningsPlayerA": 0, "inningsPlayerB": 0, "highBreaksA": "", "highBreaksB": "", "runoutsA": 0, "runoutsB": 0, "lagWinner": "", "table": [], "tournamentId": 9203524, "challengeId": 0, "starttime": "2021-08-31T20:13:00", "stoptime": "2021-08-31T20:31:54", "matchstatus": "finished", "matchstatusCode": 2, "bestOfSets": 0, "useInnings": false, "frames": [], "properties": [], "sets": [], "curVersion": 85, "notes": [], "matchType": 0, "videoLink": "", "comment": "", "winnerNext": "", "loserNext": ""}, {"matchId": 9203976, "matchno": 20, "roundName": "Round 3", "round": 3, "playerA": {"playerId": 5665150, "name": "\u0141ukasz Wojtkowiak", "firstname": "\u0141ukasz", "lastname": "Wojtkowiak", "url": "https://cuescore.com/player/%C5%81ukasz+Wojtkowiak/5665150", "image": "https://img.cuescore.com/image/9/4/98e6516dcca6383eab1da5a079164508.png?t=1565342357", "country": {"name": "Poland", "alpha3": "POL", "image": "https://cuescore.com/img/flags/png-country-4x2-none/res-640x480/pl.png", "continent": "Europe"}, "represents": []}, "playerB": {"playerId": 2383646, "name": "Piotr Niewczas", "firstname": "Piotr", "lastname": "Niewczas", "url": "https://cuescore.com/player/Piotr+Niewczas/2383646", "image": "https://img.cuescore.com/image/5/4/5859c1d9450d0be5004521cfdb2938c9.png?t=1551456237", "country": {"name": "Poland", "alpha3": "POL", "image": "https://cuescore.com/img/flags/png-country-4x2-none/res-640x480/pl.png", "continent": "Europe"}, "represents": []}, "scoreA": 3, "scoreB": 4, "raceTo": 4, "discipline": "9-Ball", "disciplineId": 3, "branch": 1, "penalty": 0, "groupNo": 2, "inningsPlayerA": 0, "inningsPlayerB": 0, "highBreaksA": "", "highBreaksB": "", "runoutsA": 0, "runoutsB": 0, "lagWinner": "", "table": [], "tournamentId": 9203524, "challengeId": 0, "starttime": "2021-08-31T21:08:00", "stoptime": "2021-08-31T21:51:53", "matchstatus": "finished", "matchstatusCode": 2, "bestOfSets": 0, "useInnings": false, "frames": [], "properties": [], "sets": [], "curVersion": 85, "notes": [], "matchType": 0, "videoLink": "", "comment": "", "winnerNext": "", "loserNext": ""}, {"matchId": 9203977, "matchno": 21, "roundName": "Round 3", "round": 3, "playerA": {"playerId": 2380196, "name": "Tomasz Stachera", "firstname": "Tomasz", "lastname": "Stachera", "url": "https://cuescore.com/player/Tomasz+Stachera/2380196", "image": "https://img.cuescore.com/image/d/4/d49717b5d8dad07dee1f23f9245e1750.png?t=1580259634", "country": {"name": "Poland", "alpha3": "POL", "image": "https://cuescore.com/img/flags/png-country-4x2-none/res-640x480/pl.png", "continent": "Europe"}, "represents": []}, "playerB": {"playerId": 8846680, "name": "Hubert Biczyk", "firstname": "Hubert", "lastname": "Biczyk", "url": "https://cuescore.com/player/Hubert+Biczyk/8846680", "image": "https://img.cuescore.com/image/8/4/862c792ba8eb7f97e626fbe6cbcc59f6.png", "country": {"name": "Poland", "alpha3": "POL", "image": "https://cuescore.com/img/flags/png-country-4x2-none/res-640x480/pl.png", "continent": "Europe"}, "represents": []}, "scoreA": 4, "scoreB": 0, "raceTo": 4, "discipline": "9-Ball", "disciplineId": 3, "branch": 1, "penalty": 0, "groupNo": 3, "inningsPlayerA": 0, "inningsPlayerB": 0, "highBreaksA": "", "highBreaksB": "", "runoutsA": 0, "runoutsB": 0, "lagWinner": "", "table": [], "tournamentId": 9203524, "challengeId": 0, "starttime": "2021-08-31T19:19:00", "stoptime": "2021-08-31T19:42:34", "matchstatus": "finished", "matchstatusCode": 2, "bestOfSets": 0, "useInnings": false, "frames": [], "properties": [], "sets": [], "curVersion": 85, "notes": [], "matchType": 0, "videoLink": "", "comment": "", "winnerNext": "", "loserNext": ""}, {"matchId": 9203978, "matchno": 22, "roundName": "Round 3", "round": 3, "playerA": {"playerId": 2180579, "name": "Marta Wawrzyn", "firstname": "Marta", "lastname": "Wawrzyn", "url": "https://cuescore.com/player/Marta+Wawrzyn/2180579", "image": "https://img.cuescore.com/image/e/4/eff8001937f0a627a1c033854110bbe7.png?t=1737981612", "country": {"name": "Poland", "alpha3": "POL", "image": "https://cuescore.com/img/flags/png-country-4x2-none/res-640x480/pl.png", "continent": "Europe"}, "represents": []}, "playerB": {"playerId": 2555617, "name": "Witek Stachera", "firstname": "Witek", "lastname": "Stachera", "url": "https://cuescore.com/player/Witek+Stachera/2555617", "image": "https://img.cuescore.com/image/5/4/5479e32916eecaa8f48b155f7419893e.png?t=1548169639", "country": {"name": "Poland", "alpha3": "POL", "image": "https://cuescore.com/img/flags/png-country-4x2-none/res-640x480/pl.png", "continent": "Europe"}, "represents": []}, "scoreA": 4, "scoreB": 0, "raceTo": 4, "discipline": "9-Ball", "disciplineId": 3, "branch": 1, "penalty": 0, "groupNo": 3, "inningsPlayerA": 0, "inningsPlayerB": 0, "highBreaksA": "", "highBreaksB": "", "runoutsA": 0, "runoutsB": 0, "lagWinner": "", "table": [], "tournamentId": 9203524, "challengeId": 0, "starttime": "2021-08-31T19:42:00", "stoptime": "2021-08-31T20:29:13", "matchstatus": "finished", "matchstatusCode": 2, "bestOfSets": 0, "useInnings": false, "frames": [], "properties": [], "sets": [], "curVersion": 85, "notes": [], "matchType": 0, "videoLink": "", "comment": "", "winnerNext": "", "loserNext": ""}, {"matchId": 9203979, "matchno": 23, "roundName": "Round 3", "round": 3, "playerA": {"playerId": 1634586, "name": "Marcin Kubalski", "firstname": "Marcin", "lastname": "Kubalski", "url": "https://cuescore.com/player/Marcin+Kubalski/1634586", "image": "https://img.cuescore.com/image/6/4/634670d25cfb0b8494e08327b2bb74b4.png?t=1736761259", "country": {"name": "Poland", "alpha3": "POL", "image": "https://cuescore.com/img/flags/png-country-4x2-none/res-640x480/pl.png", "continent": "Europe"}, "represents": {"organizationId": 4991658, "stub": "snookerzone", "name": "Snooker.Zone", "url": "https://cuescore.com/snookerzone", "logo": "//img.cuescore.com/image/2/2/2c18635ebc6f2e574949d524d3026197.png?t=1551972415", "profileColor": ""}}, "playerB": {"playerId": 4890123, "name": "Les\u0142aw \u0141ukaszewicz", "firstname": "Les\u0142aw", "lastname": "\u0141ukaszewicz", "url": "https://cuescore.com/player/Les%C5%82aw+%C5%81ukaszewicz/4890123", "image": "https://img.cuescore.com/image/c/4/c4451d50e12c1b75282716bc9ae69017.png?t=1631561718", "country": {"name": "Poland", "alpha3": "POL", "image": "https://cuescore.com/img/flags/png-country-4x2-none/res-640x480/pl.png", "continent": "Europe"}, "represents": []}, "scoreA": 3, "scoreB": 4, "raceTo": 4, "discipline": "9-Ball", "disciplineId": 3, "branch": 1, "penalty": 0, "groupNo": 4, "inningsPlayerA": 0, "inningsPlayerB": 0, "highBreaksA": "", "highBreaksB": "", "runoutsA": 0, "runoutsB": 0, "lagWinner": "", "table": [], "tournamentId": 9203524, "challengeId": 0, "starttime": "2021-08-31T20:33:00", "stoptime": "2021-08-31T21:02:14", "matchstatus": "finished", "matchstatusCode": 2, "bestOfSets": 0, "useInnings": false, "frames": [], "properties": [], "sets": [], "curVersion": 85, "notes": [], "matchType": 0, "videoLink": "", "comment": "", "winnerNext": "", "loserNext": ""}, {"matchId": 9203980, "matchno": 24, "roundName": "Round 3", "round": 3, "playerA": {"playerId": 4895428, "name": "Ewelina Pi\u015blewska", "firstname": "Ewelina", "lastname": "Pi\u015blewska", "url": "https://cuescore.com/player/Ewelina+Pi%C5%9Blewska/4895428", "image": "https://img.cuescore.com/image/7/4/7ca8efed4116a0d94fc6420732710509.png?t=1615748426", "country": {"name": "Poland", "alpha3": "POL", "image": "https://cuescore.com/img/flags/png-country-4x2-none/res-640x480/pl.png", "continent": "Europe"}, "represents": []}, "playerB": {"playerId": 1718455, "name": "Brajan Sawicki", "firstname": "Brajan", "lastname": "Sawicki", "url": "https://cuescore.com/player/Brajan+Sawicki/1718455", "image": "https://img.cuescore.com/image/7/4/7d0eac9908743891ca13c3d70d315319.png?t=1744044465", "country": {"name": "Poland", "alpha3": "POL", "image": "https://cuescore.com/img/flags/png-country-4x2-none/res-640x480/pl.png", "continent": "Europe"}, "represents": []}, "scoreA": 1, "scoreB": 4, "raceTo": 4, "discipline": "9-Ball", "disciplineId": 3, "branch": 1, "penalty": 0, "groupNo": 4, "inningsPlayerA": 0, "inningsPlayerB": 0, "highBreaksA": "", "highBreaksB": "", "runoutsA": 0, "runoutsB": 0, "lagWinner": "", "table": [], "tournamentId": 9203524, "challengeId": 0, "starttime": "2021-08-31T19:19:00", "stoptime": "2021-08-31T19:50:20", "matchstatus": "finished", "matchstatusCode": 2, "bestOfSets": 0, "useInnings": false, "frames": [], "properties": [], "sets": [], "curVersion": 85, "notes": [], "matchType": 0, "videoLink": "", "comment": "", "winnerNext": "", "loserNext": ""}, {"matchId": 9203981, "matchno": 25, "roundName": "Quarter final", "round": 4, "playerA": {"playerId": 1660831, "name": "Sebastian Szymkowski", "firstname": "Sebastian", "lastname": "Szymkowski", "url": "https://cuescore.com/player/Sebastian+Szymkowski/1660831", "image": "https://img.cuescore.com/image/8/4/8e25b60ff30ecb15ccb65e9c5875c024.png?t=1758874499", "country": {"name": "Poland", "alpha3": "POL", "image": "https://cuescore.com/img/flags/png-country-4x2-none/res-640x480/pl.png", "continent": "Europe"}, "represents": []}, "playerB": {"playerId": 2380196, "name": "Tomasz Stachera", "firstname": "Tomasz", "lastname": "Stachera", "url": "https://cuescore.com/player/Tomasz+Stachera/2380196", "image": "https://img.cuescore.com/image/d/4/d49717b5d8dad07dee1f23f9245e1750.png?t=1580259634", "country": {"name": "Poland", "alpha3": "POL", "image": "https://cuescore.com/img/flags/png-country-4x2-none/res-640x480/pl.png", "continent": "Europe"}, "represents": []}, "scoreA": 4, "scoreB": 0, "raceTo": 4, "discipline": "9-Ball", "disciplineId": 3, "branch": 1, "penalty": 0, "groupNo": 0, "inningsPlayerA": 0, "inningsPlayerB": 0, "highBreaksA": "", "highBreaksB": "", "runoutsA": 0, "runoutsB": 0, "lagWinner": "", "table": [], "tournamentId": 9203524, "challengeId": 0, "starttime": "2021-08-31T21:56:00", "stoptime": "2021-08-31T22:17:17", "matchstatus": "finished", "matchstatusCode": 2, "bestOfSets": 0, "useInnings": false, "frames": [], "properties": [], "sets": [], "curVersion": 85, "notes": [], "matchType": 0, "videoLink": "", "comment": "", "winnerNext": 29, "loserNext": ""}, {"matchId": 9203982, "matchno": 26, "roundName": "Quarter final", "round": 4, "playerA": {"playerId": 2383646, "name": "Piotr Niewczas", "firstname": "Piotr", "lastname": "Niewczas", "url": "https://cuescore.com/player/Piotr+Niewczas/2383646", "image": "https://img.cuescore.com/image/5/4/5859c1d9450d0be5004521cfdb2938c9.png?t=1551456237", "country": {"name": "Poland", "alpha3": "POL", "image": "https://cuescore.com/img/flags/png-country-4x2-none/res-640x480/pl.png", "continent": "Europe"}, "represents": []}, "playerB": {"playerId": 1634586, "name": "Marcin Kubalski", "firstname": "Marcin", "lastname": "Kubalski", "url": "https://cuescore.com/player/Marcin+Kubalski/1634586", "image": "https://img.cuescore.com/image/6/4/634670d25cfb0b8494e08327b2bb74b4.png?t=1736761259", "country": {"name": "Poland", "alpha3": "POL", "image": "https://cuescore.com/img/flags/png-country-4x2-none/res-640x480/pl.png", "continent": "Europe"}, "represents": {"organizationId": 4991658, "stub": "snookerzone", "name": "Snooker.Zone", "url": "https://cuescore.com/snookerzone", "logo": "//img.cuescore.com/image/2/2/2c18635ebc6f2e574949d524d3026197.png?t=1551972415", "profileColor": ""}}, "scoreA": 2, "scoreB": 4, "raceTo": 4, "discipline": "9-Ball", "disciplineId": 3, "branch": 1, "penalty": 0, "groupNo": 0, "inningsPlayerA": 0, "inningsPlayerB": 0, "highBreaksA": "", "highBreaksB": "", "runoutsA": 0, "runoutsB": 0, "lagWinner": "", "table": [], "tournamentId": 9203524, "challengeId": 0, "starttime": "2021-08-31T21:56:00", "stoptime": "2021-08-31T22:35:34", "matchstatus": "finished", "matchstatusCode": 2, "bestOfSets": 0, "useInnings": false, "frames": [], "properties": [], "sets": [], "curVersion": 85, "notes": [], "matchType": 0, "videoLink": "", "comment": "", "winnerNext": 29, "loserNext": ""}, {"matchId": 9203983, "matchno": 27, "roundName": "Quarter final", "round": 4, "playerA": {"playerId": 2180579, "name": "Marta Wawrzyn", "firstname": "Marta", "lastname": "Wawrzyn", "url": "https://cuescore.com/player/Marta+Wawrzyn/2180579", "image": "https://img.cuescore.com/image/e/4/eff8001937f0a627a1c033854110bbe7.png?t=1737981612", "country": {"name": "Poland", "alpha3": "POL", "image": "https://cuescore.com/img/flags/png-country-4x2-none/res-640x480/pl.png", "continent": "Europe"}, "represents": []}, "playerB": {"playerId": 8473064, "name": "Damian Tokarski", "firstname": "Damian", "lastname": "Tokarski", "url": "https://cuescore.com/player/Damian+Tokarski/8473064", "image": "https://img.cuescore.com/image/8/4/862c792ba8eb7f97e626fbe6cbcc59f6.png", "country": {"name": "Poland", "alpha3": "POL", "image": "https://cuescore.com/img/flags/png-country-4x2-none/res-640x480/pl.png", "continent": "Europe"}, "represents": []}, "scoreA": 4, "scoreB": 0, "raceTo": 4, "discipline": "9-Ball", "disciplineId": 3, "branch": 1, "penalty": 0, "groupNo": 0, "inningsPlayerA": 0, "inningsPlayerB": 0, "highBreaksA": "", "highBreaksB": "", "runoutsA": 0, "runoutsB": 0, "lagWinner": "", "table": [], "tournamentId": 9203524, "challengeId": 0, "starttime": "2021-08-31T21:56:00", "stoptime": "2021-08-31T22:13:07", "matchstatus": "finished", "matchstatusCode": 2, "bestOfSets": 0, "useInnings": false, "frames": [], "properties": [], "sets": [], "curVersion": 85, "notes": [], "matchType": 0, "videoLink": "", "comment": "", "winnerNext": 30, "loserNext": ""}, {"matchId": 9203984, "matchno": 28, "roundName": "Quarter final", "round": 4, "playerA": {"playerId": 4890123, "name": "Les\u0142aw \u0141ukaszewicz", "firstname": "Les\u0142aw", "lastname": "\u0141ukaszewicz", "url": "https://cuescore.com/player/Les%C5%82aw+%C5%81ukaszewicz/4890123", "image": "https://img.cuescore.com/image/c/4/c4451d50e12c1b75282716bc9ae69017.png?t=1631561718", "country": {"name": "Poland", "alpha3": "POL", "image": "https://cuescore.com/img/flags/png-country-4x2-none/res-640x480/pl.png", "continent": "Europe"}, "represents": []}, "playerB": {"playerId": 8440979, "name": "Dawid Tonojan", "firstname": "Dawid", "lastname": "Tonojan", "url": "https://cuescore.com/player/Dawid+Tonojan/8440979", "image": "https://img.cuescore.com/image/f/4/f3eaf2f78980cd906e7ab9eb005e0480.png?t=1679557952", "country": {"name": "Poland", "alpha3": "POL", "image": "https://cuescore.com/img/flags/png-country-4x2-none/res-640x480/pl.png", "continent": "Europe"}, "represents": []}, "scoreA": 4, "scoreB": 3, "raceTo": 4, "discipline": "9-Ball", "disciplineId": 3, "branch": 1, "penalty": 0, "groupNo": 0, "inningsPlayerA": 0, "inningsPlayerB": 0, "highBreaksA": "", "highBreaksB": "", "runoutsA": 0, "runoutsB": 0, "lagWinner": "", "table": [], "tournamentId": 9203524, "challengeId": 0, "starttime": "2021-08-31T21:56:00", "stoptime": "2021-08-31T22:22:38", "matchstatus": "finished", "matchstatusCode": 2, "bestOfSets": 0, "useInnings": false, "frames": [], "properties": [], "sets": [], "curVersion": 85, "notes": [], "matchType": 0, "videoLink": "", "comment": "", "winnerNext": 30, "loserNext": ""}, {"matchId": 9203985, "matchno": 29, "roundName": "Semi final", "round": 5, "playerA": {"playerId": 1660831, "name": "Sebastian Szymkowski", "firstname": "Sebastian", "lastname": "Szymkowski", "url": "https://cuescore.com/player/Sebastian+Szymkowski/1660831", "image": "https://img.cuescore.com/image/8/4/8e25b60ff30ecb15ccb65e9c5875c024.png?t=1758874499", "country": {"name": "Poland", "alpha3": "POL", "image": "https://cuescore.com/img/flags/png-country-4x2-none/res-640x480/pl.png", "continent": "Europe"}, "represents": []}, "playerB": {"playerId": 1634586, "name": "Marcin Kubalski", "firstname": "Marcin", "lastname": "Kubalski", "url": "https://cuescore.com/player/Marcin+Kubalski/1634586", "image": "https://img.cuescore.com/image/6/4/634670d25cfb0b8494e08327b2bb74b4.png?t=1736761259", "country": {"name": "Poland", "alpha3": "POL", "image": "https://cuescore.com/img/flags/png-country-4x2-none/res-640x480/pl.png", "continent": "Europe"}, "represents": {"organizationId": 4991658, "stub": "snookerzone", "name": "Snooker.Zone", "url": "https://cuescore.com/snookerzone", "logo": "//img.cuescore.com/image/2/2/2c18635ebc6f2e574949d524d3026197.png?t=1551972415", "profileColor": ""}}, "scoreA": 4, "scoreB": 1, "raceTo": 4, "discipline": "9-Ball", "disciplineId": 3, "branch": 1, "penalty": 0, "groupNo": 0, "inningsPlayerA": 0, "inningsPlayerB": 0, "highBreaksA": "", "highBreaksB": "", "runoutsA": 0, "runoutsB": 0, "lagWinner": "", "table": [], "tournamentId": 9203524, "challengeId": 0, "starttime": "2021-08-31T22:35:00", "stoptime": "2021-08-31T23:12:02", "matchstatus": "finished", "matchstatusCode": 2, "bestOfSets": 0, "useInnings": false, "frames": [], "properties": {"penalty": []}, "sets": [], "curVersion": 85, "notes": [], "matchType": 0, "videoLink": "", "comment": "", "winnerNext": 31, "loserNext": ""}, {"matchId": 9203986, "matchno": 30, "roundName": "Semi final", "round": 5, "playerA": {"playerId": 2180579, "name": "Marta Wawrzyn", "firstname": "Marta", "lastname": "Wawrzyn", "url": "https://cuescore.com/player/Marta+Wawrzyn/2180579", "image": "https://img.cuescore.com/image/e/4/eff8001937f0a627a1c033854110bbe7.png?t=1737981612", "country": {"name": "Poland", "alpha3": "POL", "image": "https://cuescore.com/img/flags/png-country-4x2-none/res-640x480/pl.png", "continent": "Europe"}, "represents": []}, "playerB": {"playerId": 4890123, "name": "Les\u0142aw \u0141ukaszewicz", "firstname": "Les\u0142aw", "lastname": "\u0141ukaszewicz", "url": "https://cuescore.com/player/Les%C5%82aw+%C5%81ukaszewicz/4890123", "image": "https://img.cuescore.com/image/c/4/c4451d50e12c1b75282716bc9ae69017.png?t=1631561718", "country": {"name": "Poland", "alpha3": "POL", "image": "https://cuescore.com/img/flags/png-country-4x2-none/res-640x480/pl.png", "continent": "Europe"}, "represents": []}, "scoreA": 1, "scoreB": 4, "raceTo": 4, "discipline": "9-Ball", "disciplineId": 3, "branch": 1, "penalty": 0, "groupNo": 0, "inningsPlayerA": 0, "inningsPlayerB": 0, "highBreaksA": "", "highBreaksB": "", "runoutsA": 0, "runoutsB": 0, "lagWinner": "", "table": [], "tournamentId": 9203524, "challengeId": 0, "starttime": "2021-08-31T22:30:00", "stoptime": "2021-08-31T22:54:39", "matchstatus": "finished", "matchstatusCode": 2, "bestOfSets": 0, "useInnings": false, "frames": [], "properties": {"penalty": []}, "sets": [], "curVersion": 85, "notes": [], "matchType": 0, "videoLink": "", "comment": "", "winnerNext": 31, "loserNext": ""}, {"matchId": 9203987, "matchno": 31, "roundName": "Final", "round": 6, "playerA": {"playerId": 1660831, "name": "Sebastian Szymkowski", "firstname": "Sebastian", "lastname": "Szymkowski", "url": "https://cuescore.com/player/Sebastian+Szymkowski/1660831", "image": "https://img.cuescore.com/image/8/4/8e25b60ff30ecb15ccb65e9c5875c024.png?t=1758874499", "country": {"name": "Poland", "alpha3": "POL", "image": "https://cuescore.com/img/flags/png-country-4x2-none/res-640x480/pl.png", "continent": "Europe"}, "represents": []}, "playerB": {"playerId": 4890123, "name": "Les\u0142aw \u0141ukaszewicz", "firstname": "Les\u0142aw", "lastname": "\u0141ukaszewicz", "url": "https://cuescore.com/player/Les%C5%82aw+%C5%81ukaszewicz/4890123", "image": "https://img.cuescore.com/image/c/4/c4451d50e12c1b75282716bc9ae69017.png?t=1631561718", "country": {"name": "Poland", "alpha3": "POL", "image": "https://cuescore.com/img/flags/png-country-4x2-none/res-640x480/pl.png", "continent": "Europe"}, "represents": []}, "scoreA": 0, "scoreB": 4, "raceTo": 4, "discipline": "9-Ball", "disciplineId": 3, "branch": 1, "penalty": 0, "groupNo": 0, "inningsPlayerA": 0, "inningsPlayerB": 0, "highBreaksA": "", "highBreaksB": "", "runoutsA": 0, "runoutsB": 0, "lagWinner": "", "table": [], "tournamentId": 9203524, "challengeId": 0, "starttime": "2021-08-31T23:12:00", "stoptime": "2021-08-31T23:32:28", "matchstatus": "finished", "matchstatusCode": 2, "bestOfSets": 0, "useInnings": false, "frames": [], "properties": {"penalty": []}, "sets": [], "curVersion": 85, "notes": [], "matchType": 0, "videoLink": "", "comment": "", "winnerNext": "", "loserNext": ""}], "rankings": [{"rankingId": 8262697, "name": "Ranking Warszawy 2020/21", "url": "https://cuescore.com/ranking/Ranking+Warszawy+2020%252F21/8262697", "branch": 1, "pointsystem": 0, "bestOf": 0, "season": 2020}, {"rankingId": 8885932, "name": "Eighty Nine Trophy V", "url": "https://cuescore.com/ranking/Eighty+Nine+Trophy+V/8885932", "branch": 1, "pointsystem": 0, "bestOf": 0, "season": 2021}], "access": [1620195], "id": "9203524"}